cadl/__init__.py
cadl/batch_norm.py
cadl/celeb_vaegan.py
cadl/charrnn.py
cadl/cornell.py
cadl/cycle_gan.py
cadl/dataset_utils.py
cadl/datasets.py
cadl/deepdream.py
cadl/dft.py
cadl/draw.py
cadl/fastwavenet.py
cadl/gan.py
cadl/gif.py
cadl/glove.py
cadl/i2v.py
cadl/inception.py
cadl/librispeech.py
cadl/magenta_utils.py
cadl/mdn.py
cadl/nb_utils.py
cadl/nsynth.py
cadl/pixelcnn.py
cadl/pixelrnn.py
cadl/seq2seq.py
cadl/skipthoughts.py
cadl/squeezenet.py
cadl/stats.py
cadl/stylenet.py
cadl/tedlium.py
cadl/timit.py
cadl/utils.py
cadl/vae.py
cadl/vaegan.py
cadl/vctk.py
cadl/vgg16.py
cadl/wavenet.py
cadl/wavenet_utils.py
cadl/word2vec.py
cadl/deprecated/__init__.py
cadl/deprecated/seq2seq.py
cadl/deprecated/seq2seq_model.py
cadl/deprecated/seq2seq_utils.py
cadl-1.1.0.dist-info/DESCRIPTION.rst
cadl-1.1.0.dist-info/METADATA
cadl-1.1.0.dist-info/RECORD
cadl-1.1.0.dist-info/WHEEL
cadl-1.1.0.dist-info/metadata.json
cadl-1.1.0.dist-info/top_level.txt
