Metadata-Version: 2.0
Name: cadl
Version: 1.1.0
Summary: Creative Applications of Deep Learning with TensorFlow
Home-page: https://github.com/pkmital/pycadl
Author: Parag Mital
Author-email: parag@pkmital.com
License: UNKNOWN
Download-URL: https://github.com/pkmital/pycadl/archive/v1.1.0.tar.gz
Platform: UNKNOWN
Classifier: Intended Audience :: Developers
Classifier: Natural Language :: English
Classifier: Programming Language :: Python :: 3.5
Classifier: Programming Language :: Python :: 3.6
Requires-Dist: bs4
Requires-Dist: librosa
Requires-Dist: magenta
Requires-Dist: matplotlib
Requires-Dist: nltk
Requires-Dist: numpy
Requires-Dist: requests
Requires-Dist: scikit-image
Requires-Dist: scikit-learn
Requires-Dist: scipy
Requires-Dist: tensorflow
